goldappletracker/goldappletracker/__init__.py
goldappletracker/tests/__init__.py
goldappletracker-0.1.0.dist-info/METADATA
goldappletracker-0.1.0.dist-info/WHEEL
goldappletracker-0.1.0.dist-info/RECORD
