Metadata-Version: 2.1
Name: goldappletracker
Version: 0.1.0
Summary: poetry file
Author: stardain
Requires-Python: >=3.11,<4.0
Classifier: Programming Language :: Python :: 3
Classifier: Programming Language :: Python :: 3.11
Classifier: Programming Language :: Python :: 3.12
Requires-Dist: bs4 (>=0.0.2,<0.0.3)
Requires-Dist: fastapi (>=0.111.1,<0.112.0)
Requires-Dist: pymongo (>=4.8.0,<5.0.0)
Requires-Dist: requests (>=2.32.3,<3.0.0)
